YW_jaz/__init__.py
YW_jaz/calc_ratio.py
YW_jaz/get_all.py
YW_jaz/get_calibration.py
YW_jaz/get_regression.py
YW_jaz/match_time.py
YW_jaz/read_jaz.py
YW_jaz-0.1.0.dist-info/METADATA
YW_jaz-0.1.0.dist-info/WHEEL
YW_jaz-0.1.0.dist-info/top_level.txt
YW_jaz-0.1.0.dist-info/RECORD
