Metadata-Version: 2.1
Name: YW_jaz
Version: 0.1.0
Summary: YWs jaz processing tool
Author: Yulun Wu
Author-email: yulunwu8@gmail.com
Classifier: Programming Language :: Python :: 3
Requires-Python: >=3.8
Requires-Dist: matplotlib
Requires-Dist: pandas
Requires-Dist: numpy
